{"config":{"output_file":null,"full_docs":false,"pub_only":false,"reachable_only":false,"distro_crate":false,"signatures":false,"borrow_data":false},"version":"0.19.0","compilation":{"directory":"/Users/rh01/learn-rust/reference","program":"/Users/rh01/.rustup/toolchains/stable-x86_64-apple-darwin/bin/rls","arguments":[],"output":"/Users/rh01/learn-rust/reference/target/rls/debug/deps/libreference-bd2f958fe7761aa9.rmeta"},"prelude":{"crate_id":{"name":"reference","disambiguator":[12690712341727827636,17132806440843995932]},"crate_root":"src","external_crates":[{"file_name":"/Users/rh01/learn-rust/reference/src/main.rs","num":1,"id":{"name":"std","disambiguator":[5023031535946102806,1519945200772436769]}},{"file_name":"/Users/rh01/learn-rust/reference/src/main.rs","num":2,"id":{"name":"core","disambiguator":[14971710667112632204,3779288994815239424]}},{"file_name":"/Users/rh01/learn-rust/reference/src/main.rs","num":3,"id":{"name":"compiler_builtins","disambiguator":[13929365297553886769,10835487607786681578]}},{"file_name":"/Users/rh01/learn-rust/reference/src/main.rs","num":4,"id":{"name":"rustc_std_workspace_core","disambiguator":[1703814022776569128,10551764917560457909]}},{"file_name":"/Users/rh01/learn-rust/reference/src/main.rs","num":5,"id":{"name":"alloc","disambiguator":[10905289896639819248,12378153447800695556]}},{"file_name":"/Users/rh01/learn-rust/reference/src/main.rs","num":6,"id":{"name":"libc","disambiguator":[9875817922157896832,6525866999979462444]}},{"file_name":"/Users/rh01/learn-rust/reference/src/main.rs","num":7,"id":{"name":"unwind","disambiguator":[16327553567805037396,13803445574918473825]}},{"file_name":"/Users/rh01/learn-rust/reference/src/main.rs","num":8,"id":{"name":"cfg_if","disambiguator":[8522830685719941355,5926318803845271184]}},{"file_name":"/Users/rh01/learn-rust/reference/src/main.rs","num":9,"id":{"name":"backtrace","disambiguator":[1264957467986197796,4307507407817205004]}},{"file_name":"/Users/rh01/learn-rust/reference/src/main.rs","num":10,"id":{"name":"rustc_demangle","disambiguator":[14209462635893683258,5261725291371373837]}},{"file_name":"/Users/rh01/learn-rust/reference/src/main.rs","num":11,"id":{"name":"backtrace_sys","disambiguator":[17767136569084421189,11517709274149150814]}},{"file_name":"/Users/rh01/learn-rust/reference/src/main.rs","num":12,"id":{"name":"hashbrown","disambiguator":[6927829448697524174,8965120119738204078]}},{"file_name":"/Users/rh01/learn-rust/reference/src/main.rs","num":13,"id":{"name":"rustc_std_workspace_alloc","disambiguator":[16003526636929696339,16081502929097916775]}},{"file_name":"/Users/rh01/learn-rust/reference/src/main.rs","num":14,"id":{"name":"panic_unwind","disambiguator":[15776410874500773192,14769858709110954983]}},{"file_name":"/Users/rh01/learn-rust/reference/src/main.rs","num":15,"id":{"name":"test","disambiguator":[6697405366180473236,17970625050479378427]}},{"file_name":"/Users/rh01/learn-rust/reference/src/main.rs","num":16,"id":{"name":"getopts","disambiguator":[18378027985836396866,3213649631161010016]}},{"file_name":"/Users/rh01/learn-rust/reference/src/main.rs","num":17,"id":{"name":"rustc_std_workspace_std","disambiguator":[13173608998171263398,4940949202435444023]}},{"file_name":"/Users/rh01/learn-rust/reference/src/main.rs","num":18,"id":{"name":"unicode_width","disambiguator":[10240533323609406680,8013584429063998937]}},{"file_name":"/Users/rh01/learn-rust/reference/src/main.rs","num":19,"id":{"name":"term","disambiguator":[4046945324310762435,7572862975781498444]}}],"span":{"file_name":"src/main.rs","byte_start":0,"byte_end":2069,"line_start":1,"line_end":66,"column_start":1,"column_end":2}},"imports":[],"defs":[{"kind":"Mod","id":{"krate":0,"index":0},"span":{"file_name":"src/main.rs","byte_start":0,"byte_end":2069,"line_start":1,"line_end":66,"column_start":1,"column_end":2},"name":"","qualname":"::","value":"src/main.rs","parent":null,"children":[{"krate":0,"index":10},{"krate":0,"index":11},{"krate":0,"index":12},{"krate":0,"index":13},{"krate":0,"index":14}],"decl_id":null,"docs":"","sig":null,"attributes":[]},{"kind":"Function","id":{"krate":0,"index":12},"span":{"file_name":"src/main.rs","byte_start":3,"byte_end":7,"line_start":1,"line_end":1,"column_start":4,"column_end":8},"name":"main","qualname":"::main","value":"fn () -> ()","parent":null,"children":[],"decl_id":null,"docs":"","sig":null,"attributes":[{"value":"allow(dead_code)","span":{"file_name":"src/main.rs","byte_start":0,"byte_end":0,"line_start":1,"line_end":1,"column_start":1,"column_end":1}}]},{"kind":"Local","id":{"krate":0,"index":4294967283},"span":{"file_name":"src/main.rs","byte_start":24,"byte_end":26,"line_start":2,"line_end":2,"column_start":13,"column_end":15},"name":"s1","qualname":"s1$12","value":"std::string::String","parent":null,"children":[],"decl_id":null,"docs":"","sig":null,"attributes":[]},{"kind":"Local","id":{"krate":0,"index":4294967276},"span":{"file_name":"src/main.rs","byte_start":61,"byte_end":64,"line_start":4,"line_end":4,"column_start":9,"column_end":12},"name":"len","qualname":"len$19","value":"usize","parent":null,"children":[],"decl_id":null,"docs":"","sig":null,"attributes":[]},{"kind":"Local","id":{"krate":0,"index":4294967267},"span":{"file_name":"src/main.rs","byte_start":367,"byte_end":369,"line_start":14,"line_end":14,"column_start":13,"column_end":15},"name":"r1","qualname":"r1$28","value":"&mut std::string::String","parent":null,"children":[],"decl_id":null,"docs":"","sig":null,"attributes":[]},{"kind":"Local","id":{"krate":0,"index":4294967260},"span":{"file_name":"src/main.rs","byte_start":511,"byte_end":512,"line_start":21,"line_end":21,"column_start":17,"column_end":18},"name":"s","qualname":"s$35","value":"std::string::String","parent":null,"children":[],"decl_id":null,"docs":"","sig":null,"attributes":[]},{"kind":"Local","id":{"krate":0,"index":4294967253},"span":{"file_name":"src/main.rs","byte_start":551,"byte_end":553,"line_start":23,"line_end":23,"column_start":13,"column_end":15},"name":"r1","qualname":"r1$42","value":"&std::string::String","parent":null,"children":[],"decl_id":null,"docs":"","sig":null,"attributes":[]},{"kind":"Local","id":{"krate":0,"index":4294967248},"span":{"file_name":"src/main.rs","byte_start":585,"byte_end":587,"line_start":24,"line_end":24,"column_start":13,"column_end":15},"name":"r2","qualname":"r2$47","value":"&std::string::String","parent":null,"children":[],"decl_id":null,"docs":"","sig":null,"attributes":[]},{"kind":"Local","id":{"krate":0,"index":4294967243},"span":{"file_name":"src/main.rs","byte_start":709,"byte_end":711,"line_start":28,"line_end":28,"column_start":13,"column_end":15},"name":"r3","qualname":"r3$52","value":"&mut std::string::String","parent":null,"children":[],"decl_id":null,"docs":"","sig":null,"attributes":[]},{"kind":"Local","id":{"krate":0,"index":4294967236},"span":{"file_name":"src/main.rs","byte_start":1444,"byte_end":1445,"line_start":52,"line_end":52,"column_start":21,"column_end":22},"name":"s","qualname":"::calculate_length::s","value":"&mut std::string::String","parent":null,"children":[],"decl_id":null,"docs":"","sig":null,"attributes":[]},{"kind":"Function","id":{"krate":0,"index":13},"span":{"file_name":"src/main.rs","byte_start":1427,"byte_end":1443,"line_start":52,"line_end":52,"column_start":4,"column_end":20},"name":"calculate_length","qualname":"::calculate_length","value":"fn (s: &mut String) -> usize","parent":null,"children":[],"decl_id":null,"docs":"","sig":null,"attributes":[]}],"impls":[],"refs":[{"kind":"Function","span":{"file_name":"src/main.rs","byte_start":37,"byte_end":41,"line_start":2,"line_end":2,"column_start":26,"column_end":30},"ref_id":{"krate":2,"index":2223}},{"kind":"Type","span":{"file_name":"src/main.rs","byte_start":29,"byte_end":35,"line_start":2,"line_end":2,"column_start":18,"column_end":24},"ref_id":{"krate":5,"index":4325}},{"kind":"Function","span":{"file_name":"src/main.rs","byte_start":67,"byte_end":83,"line_start":4,"line_end":4,"column_start":15,"column_end":31},"ref_id":{"krate":0,"index":13}},{"kind":"Variable","span":{"file_name":"src/main.rs","byte_start":89,"byte_end":91,"line_start":4,"line_end":4,"column_start":37,"column_end":39},"ref_id":{"krate":0,"index":4294967283}},{"kind":"Variable","span":{"file_name":"src/main.rs","byte_start":299,"byte_end":301,"line_start":10,"line_end":10,"column_start":43,"column_end":45},"ref_id":{"krate":0,"index":4294967283}},{"kind":"Variable","span":{"file_name":"src/main.rs","byte_start":303,"byte_end":306,"line_start":10,"line_end":10,"column_start":47,"column_end":50},"ref_id":{"krate":0,"index":4294967276}},{"kind":"Variable","span":{"file_name":"src/main.rs","byte_start":377,"byte_end":379,"line_start":14,"line_end":14,"column_start":23,"column_end":25},"ref_id":{"krate":0,"index":4294967283}},{"kind":"Variable","span":{"file_name":"src/main.rs","byte_start":471,"byte_end":473,"line_start":16,"line_end":16,"column_start":47,"column_end":49},"ref_id":{"krate":0,"index":4294967267}},{"kind":"Variable","span":{"file_name":"src/main.rs","byte_start":475,"byte_end":478,"line_start":16,"line_end":16,"column_start":51,"column_end":54},"ref_id":{"krate":0,"index":4294967276}},{"kind":"Function","span":{"file_name":"src/main.rs","byte_start":523,"byte_end":527,"line_start":21,"line_end":21,"column_start":29,"column_end":33},"ref_id":{"krate":2,"index":2223}},{"kind":"Type","span":{"file_name":"src/main.rs","byte_start":515,"byte_end":521,"line_start":21,"line_end":21,"column_start":21,"column_end":27},"ref_id":{"krate":5,"index":4325}},{"kind":"Variable","span":{"file_name":"src/main.rs","byte_start":557,"byte_end":558,"line_start":23,"line_end":23,"column_start":19,"column_end":20},"ref_id":{"krate":0,"index":4294967260}},{"kind":"Variable","span":{"file_name":"src/main.rs","byte_start":591,"byte_end":592,"line_start":24,"line_end":24,"column_start":19,"column_end":20},"ref_id":{"krate":0,"index":4294967260}},{"kind":"Variable","span":{"file_name":"src/main.rs","byte_start":637,"byte_end":639,"line_start":25,"line_end":25,"column_start":31,"column_end":33},"ref_id":{"krate":0,"index":4294967253}},{"kind":"Variable","span":{"file_name":"src/main.rs","byte_start":641,"byte_end":643,"line_start":25,"line_end":25,"column_start":35,"column_end":37},"ref_id":{"krate":0,"index":4294967248}},{"kind":"Variable","span":{"file_name":"src/main.rs","byte_start":719,"byte_end":720,"line_start":28,"line_end":28,"column_start":23,"column_end":24},"ref_id":{"krate":0,"index":4294967260}},{"kind":"Variable","span":{"file_name":"src/main.rs","byte_start":912,"byte_end":914,"line_start":31,"line_end":31,"column_start":24,"column_end":26},"ref_id":{"krate":0,"index":4294967243}},{"kind":"Type","span":{"file_name":"src/main.rs","byte_start":1453,"byte_end":1459,"line_start":52,"line_end":52,"column_start":30,"column_end":36},"ref_id":{"krate":5,"index":4325}},{"kind":"Function","span":{"file_name":"src/main.rs","byte_start":1653,"byte_end":1661,"line_start":57,"line_end":57,"column_start":7,"column_end":15},"ref_id":{"krate":5,"index":3505}},{"kind":"Variable","span":{"file_name":"src/main.rs","byte_start":1651,"byte_end":1652,"line_start":57,"line_end":57,"column_start":5,"column_end":6},"ref_id":{"krate":0,"index":4294967236}},{"kind":"Function","span":{"file_name":"src/main.rs","byte_start":1681,"byte_end":1684,"line_start":58,"line_end":58,"column_start":7,"column_end":10},"ref_id":{"krate":5,"index":3526}},{"kind":"Variable","span":{"file_name":"src/main.rs","byte_start":1679,"byte_end":1680,"line_start":58,"line_end":58,"column_start":5,"column_end":6},"ref_id":{"krate":0,"index":4294967236}}],"macro_refs":[],"relations":[]}